{
  "name": "Meridian Weekly Lint",
  "nodes": [
    {
      "parameters": {
        "rule": {
          "interval": [
            {
              "field": "cronExpression",
              "expression": "0 7 * * 0"
            }
          ]
        }
      },
      "id": "schedule-trigger",
      "name": "Sunday 7 AM",
      "type": "n8n-nodes-base.scheduleTrigger",
      "typeVersion": 1.2,
      "position": [240, 300]
    },
    {
      "parameters": {
        "method": "POST",
        "url": "https://meridian.markahope.com/lint",
        "sendHeaders": true,
        "headerParameters": {
          "parameters": [
            {
              "name": "Authorization",
              "value": "=Bearer {{ $env.MERIDIAN_RECEIVER_TOKEN }}"
            }
          ]
        },
        "sendBody": true,
        "specifyBody": "json",
        "jsonBody": "={\"mode\": \"auto\", \"scope\": \"all\"}",
        "options": {
          "response": {
            "response": {
              "fullResponse": true
            }
          },
          "timeout": 10000
        }
      },
      "id": "http-request",
      "name": "Run Linter",
      "type": "n8n-nodes-base.httpRequest",
      "typeVersion": 4.2,
      "position": [480, 300],
      "onError": "continueRegularOutput"
    }
  ],
  "connections": {
    "Sunday 7 AM": {
      "main": [
        [
          {
            "node": "Run Linter",
            "type": "main",
            "index": 0
          }
        ]
      ]
    }
  },
  "settings": {
    "executionOrder": "v1"
  }
}
